ghdl/pattern_detector.vhd
----------------------------------------------------------------------------------
-- Company:        
-- Engineer:       simon.burkhardt
-- 
-- Create Date:    2023-04-21
-- Design Name:    AXIS pattern_detector
-- Module Name:    tb_skid - bh
-- Project Name:   
-- Target Devices: 
-- Tool Versions:  GHDL 0.37
-- Description:    bidirectional AXIS pipeline register
-- 
-- Dependencies:   
-- 
-- Revision:
-- Revision 0.01 - File Created
-- Additional Comments:
-- 
----------------------------------------------------------------------------------
library ieee;
use ieee.std_logic_1164.all;
use ieee.numeric_std.all;

entity pattern_detector is
  generic (
    -- Users to add parameters here

    -- User parameters ends
    -- Do not modify the parameters beyond this line

    -- Width of S_AXIS address bus. The slave accepts the read and write addresses of width C_S_AXIS_TDATA_WIDTH.
    C_S_AXIS_TDATA_WIDTH  : integer := 512;
    C_COMPARE_DATA_WIDTH  : integer := 32
  );
  port (
    -- Users to add ports here

    -- User ports ends
    -- Global ports
    AXIS_ACLK       : in std_logic;
    AXIS_ARESETN    : in  std_logic;

    -- Slave Stream Ports. TVALID indicates that the master is driving a valid transfer, A transfer takes place when both TVALID and TREADY are asserted. 
    S_AXIS_TVALID   : in  std_logic;
    -- TDATA is the primary payload that is used to provide the data that is passing across the interface from the master.
    S_AXIS_TDATA    : in  std_logic_vector(C_S_AXIS_TDATA_WIDTH-1 downto 0);
    -- TREADY indicates that the slave can accept a transfer in the current cycle.
    M_AXIS_TREADY   : in  std_logic;
    
    compare_pattern : in std_logic_vector(C_COMPARE_DATA_WIDTH-1 downto 0);

    match_out       : out std_logic
  );
end pattern_detector;

architecture arch_imp of pattern_detector is

  constant C_NUM_COMPARISONS : integer := (C_S_AXIS_TDATA_WIDTH/C_COMPARE_DATA_WIDTH);

  -- signals
  signal aclk    : std_logic;
  signal aresetn : std_logic;

  signal i_s_axis_tvalid : std_logic := '0';
  signal i_s_axis_tdata  : std_logic_vector(C_S_AXIS_TDATA_WIDTH-1 downto 0);
  signal i_m_axis_tready : std_logic;
  signal i_pattern       : std_logic_vector(C_COMPARE_DATA_WIDTH-1 downto 0);

  signal o_match_out     : std_logic;
  signal match_accumulator : std_logic_vector(C_NUM_COMPARISONS-1 downto 0);


begin
  -- I/O connections assignments
  aclk    <= AXIS_ACLK;
  aresetn <= AXIS_ARESETN;

  -- inputs
  i_m_axis_tready <= M_AXIS_TREADY;
  i_s_axis_tvalid <= S_AXIS_TVALID;
  i_s_axis_tdata  <= S_AXIS_TDATA;
  i_pattern <= compare_pattern;

  -- outputs
  match_out <= o_match_out;

  gen_alligned_pattern_detect : for ii in 0 to (C_NUM_COMPARISONS-1) generate
    p_compare : process(aclk)
    begin
      if rising_edge(aclk) then
        if aresetn = '0' then
          match_accumulator(ii) <= '0';
        else
          if i_s_axis_tvalid = '1' and i_m_axis_tready = '1' then
            if i_s_axis_tdata( (ii+1)*C_COMPARE_DATA_WIDTH-1 downto ii*C_COMPARE_DATA_WIDTH ) = i_pattern then
              match_accumulator(ii) <= '1';
            else
              match_accumulator(ii) <= '0';
            end if;
          else
            match_accumulator(ii) <= '0';
          end if;
        end if;
      end if;
    end process;
  end generate gen_alligned_pattern_detect;

-- o_match_out <= '0' when unsigned(match_accumulator) = 0 else '1';

  p_final_decision : process(aclk)
  begin
    if rising_edge(aclk) then
      if aresetn = '0' then
        o_match_out <= '0';
      else
        if unsigned(match_accumulator) = 0 then
          o_match_out <= '0';
        else 
          o_match_out <= '1';
        end if;
      end if;
    end if;
  end process;

end arch_imp;

ghdl/tb_pattern_trig.vhd
----------------------------------------------------------------------------------
-- Company:        
-- Engineer:       simon.burkhardt
-- 
-- Create Date:    2023-04-21
-- Design Name:    skid buffer testbench
-- Module Name:    tb_pattern_trig - bh
-- Project Name:   
-- Target Devices: 
-- Tool Versions:  GHDL 0.37
-- Description:    
-- 
-- Dependencies:   
-- 
-- Revision:
-- Revision 0.01 - File Created
-- Additional Comments:
-- 
----------------------------------------------------------------------------------

library ieee;
use ieee.std_logic_1164.all;
use ieee.numeric_std.all;

-- this testbench acts as a streaming master, sending bursts of data
-- counting from 1-4, also asserting tlast on the 4th data packet

-- the testbench itself acts as a correct streaming master which keeps the data
-- until it is acknowledged by the DUT by asserting tready.

-- the data pattern can be influenced by the user in 2 ways
-- + Tx requests are generated by changing the pattern in p_stimuli_tready
--   the master will try to send data for as long as sim_valid_data = '1'
-- + Rx acknowledgements are generated by changing the pattern in p_stimuli_tready
--   the downstream slave after the DUT will signal ready-to-receive 
--   when sim_ready_data = '1'

-- simulate both with OPT_DATA_REG = True / False
entity tb_pattern_trig is
  generic
  (
    C_S_AXIS_TDATA_WIDTH  : integer := 512;
    C_COMPARE_DATA_WIDTH  : integer := 32
  );
end tb_pattern_trig;

architecture bh of tb_pattern_trig is
  -- DUT component declaration
  component pattern_detector is
    generic (
      C_S_AXIS_TDATA_WIDTH  : integer;
      C_COMPARE_DATA_WIDTH  : integer
    );
    port (
      AXIS_ACLK       : in  std_logic;
      AXIS_ARESETN    : in  std_logic;
      S_AXIS_TVALID   : in  std_logic;
      S_AXIS_TDATA    : in  std_logic_vector(C_S_AXIS_TDATA_WIDTH-1 downto 0);
      M_AXIS_TREADY   : in  std_logic;
      compare_pattern : in  std_logic_vector(C_COMPARE_DATA_WIDTH-1 downto 0);
      match_out       : out std_logic
    );
  end component;

  constant CLK_PERIOD: TIME := 5 ns;

  signal clk   : std_logic;
  signal rst_n : std_logic;


  signal o_s_axis_tvalid   : std_logic;
  signal o_s_axis_tdata    : std_logic_vector(C_S_AXIS_TDATA_WIDTH-1 downto 0);
  signal o_m_axis_tready   : std_logic;
  signal o_compare_pattern : std_logic_vector(C_COMPARE_DATA_WIDTH-1 downto 0);
  signal i_match_out       : std_logic;

  signal clk_count : std_logic_vector(7 downto 0) := (others => '0');
begin

  -- generate clk signal
  p_clk_gen : process
  begin
   clk <= '1';
   wait for (CLK_PERIOD / 2);
   clk <= '0';
   wait for (CLK_PERIOD / 2);
   clk_count <= std_logic_vector(unsigned(clk_count) + 1);
  end process;

  -- generate initial reset
  p_reset_gen : process
  begin 
    rst_n <= '0';
    wait until rising_edge(clk);
    wait for (CLK_PERIOD / 4);
    rst_n <= '1';
    wait;
  end process;

  -- accept and ack BRESP
  p_traffic_gen : process(clk)
  begin
    if rising_edge(clk) then
      if rst_n = '0' then
        o_s_axis_tdata <= (others => '0');
        o_m_axis_tready <= '1';
        o_s_axis_tvalid <= '0';
        o_compare_pattern <= x"deadbeef";
      else
        if unsigned(clk_count) = 5 then
          o_s_axis_tdata(511 downto 511-31) <= x"deadbeef";
          o_s_axis_tvalid <= '1';
        end if;
        if unsigned(clk_count) = 6 then
          o_s_axis_tdata <= (others => '0');
          o_s_axis_tvalid <= '0';
        end if;

        if unsigned(clk_count) = 12 then
          o_s_axis_tdata(511 downto 511-31) <= x"abababab";
          o_s_axis_tvalid <= '1';
        end if;
        if unsigned(clk_count) = 13 then
          o_s_axis_tdata <= (others => '0');
          o_s_axis_tvalid <= '0';
        end if;

        if unsigned(clk_count) = 17 then
          o_s_axis_tdata(511-32 downto 511-31-32) <= x"deadbeef";
          o_s_axis_tvalid <= '1';
        end if;
        if unsigned(clk_count) = 18 then
          o_s_axis_tdata <= (others => '0');
          o_s_axis_tvalid <= '0';
        end if;

      end if;
    end if;
  end process;

-- DUT instance and connections
  pattern_detector_inst : pattern_detector
    generic map (
      C_S_AXIS_TDATA_WIDTH  => C_S_AXIS_TDATA_WIDTH,
      C_COMPARE_DATA_WIDTH  => C_COMPARE_DATA_WIDTH
    )
    port map (
      AXIS_ACLK      => clk,
      AXIS_ARESETN   => rst_n,

      S_AXIS_TVALID   => o_s_axis_tvalid,
      S_AXIS_TDATA    => o_s_axis_tdata,
      M_AXIS_TREADY   => o_m_axis_tready,
      compare_pattern => o_compare_pattern,
      match_out       => i_match_out
    );

end bh;

ghdl/pattern_wave.vcd
$date
  Thu Apr 27 14:48:11 2023
$end
$version
  GHDL v0
$end
$timescale
  1 fs
$end
$scope module standard $end
$upscope $end
$scope module std_logic_1164 $end
$upscope $end
$scope module numeric_std $end
$upscope $end
$scope module tb_pattern_trig $end
$var reg 1 ! clk $end
$var reg 1 " rst_n $end
$var reg 1 # o_s_axis_tvalid $end
$var reg 512 $ o_s_axis_tdata[511:0] $end
$var reg 1 % o_m_axis_tready $end
$var reg 32 & o_compare_pattern[31:0] $end
$var reg 1 ' i_match_out $end
$var reg 8 ( clk_count[7:0] $end
$scope module pattern_detector_inst $end
$var reg 1 ) axis_aclk $end
$var reg 1 * axis_aresetn $end
$var reg 1 + s_axis_tvalid $end
$var reg 512 , s_axis_tdata[511:0] $end
$var reg 1 - m_axis_tready $end
$var reg 32 . compare_pattern[31:0] $end
$var reg 1 / match_out $end
$var reg 1 0 aclk $end
$var reg 1 1 aresetn $end
$var reg 1 2 i_s_axis_tvalid $end
$var reg 512 3 i_s_axis_tdata[511:0] $end
$var reg 1 4 i_m_axis_tready $end
$var reg 32 5 i_pattern[31:0] $end
$var reg 1 6 o_match_out $end
$var reg 16 7 match_accumulator[15:0] $end
$scope module gen_alligned_pattern_detect(0) $end
$upscope $end
$scope module gen_alligned_pattern_detect(1) $end
$upscope $end
$scope module gen_alligned_pattern_detect(2) $end
$upscope $end
$scope module gen_alligned_pattern_detect(3) $end
$upscope $end
$scope module gen_alligned_pattern_detect(4) $end
$upscope $end
$scope module gen_alligned_pattern_detect(5) $end
$upscope $end
$scope module gen_alligned_pattern_detect(6) $end
$upscope $end
$scope module gen_alligned_pattern_detect(7) $end
$upscope $end
$scope module gen_alligned_pattern_detect(8) $end
$upscope $end
$scope module gen_alligned_pattern_detect(9) $end
$upscope $end
$scope module gen_alligned_pattern_detect(10) $end
$upscope $end
$scope module gen_alligned_pattern_detect(11) $end
$upscope $end
$scope module gen_alligned_pattern_detect(12) $end
$upscope $end
$scope module gen_alligned_pattern_detect(13) $end
$upscope $end
$scope module gen_alligned_pattern_detect(14) $end
$upscope $end
$scope module gen_alligned_pattern_detect(15) $end
$upscope $end
$upscope $end
$upscope $end
$enddefinitions $end
#0
1!
0"
U#
bUUUUUUUUUUUUUUUUUUUUUUUUUUUUUUUUUUUUUUUUUUUUUUUUUUUUUUUUUUUUUUUUUUUUUUUUUUUUUUUUUUUUUUUUUUUUUUUUUUUUUUUUUUUUUUUUUUUUUUUUUUUUUUUUUUUUUUUUUUUUUUUUUUUUUUUUUUUUUUUUUUUUUUUUUUUUUUUUUUUUUUUUUUUUUUUUUUUUUUUUUUUUUUUUUUUUUUUUUUUUUUUUUUUUUUUUUUUUUUUUUUUUUUUUUUUUUUUUUUUUUUUUUUUUUUUUUUUUUUUUUUUUUUUUUUUUUUUUUUUUUUUUUUUUUUUUUUUUUUUUUUUUUUUUUUUUUUUUUUUUUUUUUUUUUUUUUUUUUUUUUUUUUUUUUUUUUUUUUUUUUUUUUUUUUUUUUUUUUUUUUUUUUUUUUUUUUUUUUUUUUUUUUUUUUUUUUUUUUUUUUUUUUUUUUUUUUUUUUUUUUUUUUUUUUUUUUUUUUUUUUUUUUUUUUUUUUUUUUUUUUUUUUUUUUUUU $
U%
bUUUUUUUUUUUUUUUUUUUUUUUUUUUUUUUU &
U'
b00000000 (
1)
0*
U+
bUUUUUUUUUUUUUUUUUUUUUUUUUUUUUUUUUUUUUUUUUUUUUUUUUUUUUUUUUUUUUUUUUUUUUUUUUUUUUUUUUUUUUUUUUUUUUUUUUUUUUUUUUUUUUUUUUUUUUUUUUUUUUUUUUUUUUUUUUUUUUUUUUUUUUUUUUUUUUUUUUUUUUUUUUUUUUUUUUUUUUUUUUUUUUUUUUUUUUUUUUUUUUUUUUUUUUUUUUUUUUUUUUUUUUUUUUUUUUUUUUUUUUUUUUUUUUUUUUUUUUUUUUUUUUUUUUUUUUUUUUUUUUUUUUUUUUUUUUUUUUUUUUUUUUUUUUUUUUUUUUUUUUUUUUUUUUUUUUUUUUUUUUUUUUUUUUUUUUUUUUUUUUUUUUUUUUUUUUUUUUUUUUUUUUUUUUUUUUUUUUUUUUUUUUUUUUUUUUUUUUUUUUUUUUUUUUUUUUUUUUUUUUUUUUUUUUUUUUUUUUUUUUUUUUUUUUUUUUUUUUUUUUUUUUUUUUUUUUUUUUUUUUUUUUUUU ,
U-
bUUUUUUUUUUUUUUUUUUUUUUUUUUUUUUUU .
U/
10
01
U2
bUUUUUUUUUUUUUUUUUUUUUUUUUUUUUUUUUUUUUUUUUUUUUUUUUUUUUUUUUUUUUUUUUUUUUUUUUUUUUUUUUUUUUUUUUUUUUUUUUUUUUUUUUUUUUUUUUUUUUUUUUUUUUUUUUUUUUUUUUUUUUUUUUUUUUUUUUUUUUUUUUUUUUUUUUUUUUUUUUUUUUUUUUUUUUUUUUUUUUUUUUUUUUUUUUUUUUUUUUUUUUUUUUUUUUUUUUUUUUUUUUUUUUUUUUUUUUUUUUUUUUUUUUUUUUUUUUUUUUUUUUUUUUUUUUUUUUUUUUUUUUUUUUUUUUUUUUUUUUUUUUUUUUUUUUUUUUUUUUUUUUUUUUUUUUUUUUUUUUUUUUUUUUUUUUUUUUUUUUUUUUUUUUUUUUUUUUUUUUUUUUUUUUUUUUUUUUUUUUUUUUUUUUUUUUUUUUUUUUUUUUUUUUUUUUUUUUUUUUUUUUUUUUUUUUUUUUUUUUUUUUUUUUUUUUUUUUUUUUUUUUUUUUUUUUUUU 3
U4
bUUUUUUUUUUUUUUUUUUUUUUUUUUUUUUUU 5
U6
bUUUUUUUUUUUUUUUU 7
#2500000
0!
0)
00
#5000000
1!
0#
b00000000000000000000000000000000000000000000000000000000000000000000000000000000000000000000000000000000000000000000000000000000000000000000000000000000000000000000000000000000000000000000000000000000000000000000000000000000000000000000000000000000000000000000000000000000000000000000000000000000000000000000000000000000000000000000000000000000000000000000000000000000000000000000000000000000000000000000000000000000000000000000000000000000000000000000000000000000000000000000000000000000000000000000000000000000 $
1%
b11011110101011011011111011101111 &
0'
b00000001 (
1)
0+
b00000000000000000000000000000000000000000000000000000000000000000000000000000000000000000000000000000000000000000000000000000000000000000000000000000000000000000000000000000000000000000000000000000000000000000000000000000000000000000000000000000000000000000000000000000000000000000000000000000000000000000000000000000000000000000000000000000000000000000000000000000000000000000000000000000000000000000000000000000000000000000000000000000000000000000000000000000000000000000000000000000000000000000000000000000000 ,
1-
b11011110101011011011111011101111 .
0/
10
02
b00000000000000000000000000000000000000000000000000000000000000000000000000000000000000000000000000000000000000000000000000000000000000000000000000000000000000000000000000000000000000000000000000000000000000000000000000000000000000000000000000000000000000000000000000000000000000000000000000000000000000000000000000000000000000000000000000000000000000000000000000000000000000000000000000000000000000000000000000000000000000000000000000000000000000000000000000000000000000000000000000000000000000000000000000000000 3
14
b11011110101011011011111011101111 5
06
b0000000000000000 7
#6250000
1"
1*
11
#7500000
0!
0)
00
#10000000
1!
b00000010 (
1)
10
#12500000
0!
0)
00
#15000000
1!
b00000011 (
1)
10
#17500000
0!
0)
00
#20000000
1!
b00000100 (
1)
10
#22500000
0!
0)
00
#25000000
1!
1#
b11011110101011011011111011101111000000000000000000000000000000000000000000000000000000000000000000000000000000000000000000000000000000000000000000000000000000000000000000000000000000000000000000000000000000000000000000000000000000000000000000000000000000000000000000000000000000000000000000000000000000000000000000000000000000000000000000000000000000000000000000000000000000000000000000000000000000000000000000000000000000000000000000000000000000000000000000000000000000000000000000000000000000000000000000000000 $
b00000101 (
1)
1+
b11011110101011011011111011101111000000000000000000000000000000000000000000000000000000000000000000000000000000000000000000000000000000000000000000000000000000000000000000000000000000000000000000000000000000000000000000000000000000000000000000000000000000000000000000000000000000000000000000000000000000000000000000000000000000000000000000000000000000000000000000000000000000000000000000000000000000000000000000000000000000000000000000000000000000000000000000000000000000000000000000000000000000000000000000000000 ,
10
12
b11011110101011011011111011101111000000000000000000000000000000000000000000000000000000000000000000000000000000000000000000000000000000000000000000000000000000000000000000000000000000000000000000000000000000000000000000000000000000000000000000000000000000000000000000000000000000000000000000000000000000000000000000000000000000000000000000000000000000000000000000000000000000000000000000000000000000000000000000000000000000000000000000000000000000000000000000000000000000000000000000000000000000000000000000000000 3
#27500000
0!
0)
00
#30000000
1!
0#
b00000000000000000000000000000000000000000000000000000000000000000000000000000000000000000000000000000000000000000000000000000000000000000000000000000000000000000000000000000000000000000000000000000000000000000000000000000000000000000000000000000000000000000000000000000000000000000000000000000000000000000000000000000000000000000000000000000000000000000000000000000000000000000000000000000000000000000000000000000000000000000000000000000000000000000000000000000000000000000000000000000000000000000000000000000000 $
b00000110 (
1)
0+
b00000000000000000000000000000000000000000000000000000000000000000000000000000000000000000000000000000000000000000000000000000000000000000000000000000000000000000000000000000000000000000000000000000000000000000000000000000000000000000000000000000000000000000000000000000000000000000000000000000000000000000000000000000000000000000000000000000000000000000000000000000000000000000000000000000000000000000000000000000000000000000000000000000000000000000000000000000000000000000000000000000000000000000000000000000000 ,
10
02
b00000000000000000000000000000000000000000000000000000000000000000000000000000000000000000000000000000000000000000000000000000000000000000000000000000000000000000000000000000000000000000000000000000000000000000000000000000000000000000000000000000000000000000000000000000000000000000000000000000000000000000000000000000000000000000000000000000000000000000000000000000000000000000000000000000000000000000000000000000000000000000000000000000000000000000000000000000000000000000000000000000000000000000000000000000000 3
b1000000000000000 7
#32500000
0!
0)
00
#35000000
1!
1'
b00000111 (
1)
1/
10
16
b0000000000000000 7
#37500000
0!
0)
00
#40000000
1!
0'
b00001000 (
1)
0/
10
06
#42500000
0!
0)
00
#45000000
1!
b00001001 (
1)
10
#47500000
0!
0)
00
#50000000
1!
b00001010 (
1)
10
#52500000
0!
0)
00
#55000000
1!
b00001011 (
1)
10
#57500000
0!
0)
00
#60000000
1!
1#
b10101011101010111010101110101011000000000000000000000000000000000000000000000000000000000000000000000000000000000000000000000000000000000000000000000000000000000000000000000000000000000000000000000000000000000000000000000000000000000000000000000000000000000000000000000000000000000000000000000000000000000000000000000000000000000000000000000000000000000000000000000000000000000000000000000000000000000000000000000000000000000000000000000000000000000000000000000000000000000000000000000000000000000000000000000000 $
b00001100 (
1)
1+
b10101011101010111010101110101011000000000000000000000000000000000000000000000000000000000000000000000000000000000000000000000000000000000000000000000000000000000000000000000000000000000000000000000000000000000000000000000000000000000000000000000000000000000000000000000000000000000000000000000000000000000000000000000000000000000000000000000000000000000000000000000000000000000000000000000000000000000000000000000000000000000000000000000000000000000000000000000000000000000000000000000000000000000000000000000000 ,
10
12
b10101011101010111010101110101011000000000000000000000000000000000000000000000000000000000000000000000000000000000000000000000000000000000000000000000000000000000000000000000000000000000000000000000000000000000000000000000000000000000000000000000000000000000000000000000000000000000000000000000000000000000000000000000000000000000000000000000000000000000000000000000000000000000000000000000000000000000000000000000000000000000000000000000000000000000000000000000000000000000000000000000000000000000000000000000000 3
#62500000
0!
0)
00
#65000000
1!
0#
b00000000000000000000000000000000000000000000000000000000000000000000000000000000000000000000000000000000000000000000000000000000000000000000000000000000000000000000000000000000000000000000000000000000000000000000000000000000000000000000000000000000000000000000000000000000000000000000000000000000000000000000000000000000000000000000000000000000000000000000000000000000000000000000000000000000000000000000000000000000000000000000000000000000000000000000000000000000000000000000000000000000000000000000000000000000 $
b00001101 (
1)
0+
b00000000000000000000000000000000000000000000000000000000000000000000000000000000000000000000000000000000000000000000000000000000000000000000000000000000000000000000000000000000000000000000000000000000000000000000000000000000000000000000000000000000000000000000000000000000000000000000000000000000000000000000000000000000000000000000000000000000000000000000000000000000000000000000000000000000000000000000000000000000000000000000000000000000000000000000000000000000000000000000000000000000000000000000000000000000 ,
10
02
b00000000000000000000000000000000000000000000000000000000000000000000000000000000000000000000000000000000000000000000000000000000000000000000000000000000000000000000000000000000000000000000000000000000000000000000000000000000000000000000000000000000000000000000000000000000000000000000000000000000000000000000000000000000000000000000000000000000000000000000000000000000000000000000000000000000000000000000000000000000000000000000000000000000000000000000000000000000000000000000000000000000000000000000000000000000 3
#67500000
0!
0)
00
#70000000
1!
b00001110 (
1)
10
#72500000
0!
0)
00
#75000000
1!
b00001111 (
1)
10
#77500000
0!
0)
00
#80000000
1!
b00010000 (
1)
10
#82500000
0!
0)
00
#85000000
1!
1#
b00000000000000000000000000000000110111101010110110111110111011110000000000000000000000000000000000000000000000000000000000000000000000000000000000000000000000000000000000000000000000000000000000000000000000000000000000000000000000000000000000000000000000000000000000000000000000000000000000000000000000000000000000000000000000000000000000000000000000000000000000000000000000000000000000000000000000000000000000000000000000000000000000000000000000000000000000000000000000000000000000000000000000000000000000000000 $
b00010001 (
1)
1+
b00000000000000000000000000000000110111101010110110111110111011110000000000000000000000000000000000000000000000000000000000000000000000000000000000000000000000000000000000000000000000000000000000000000000000000000000000000000000000000000000000000000000000000000000000000000000000000000000000000000000000000000000000000000000000000000000000000000000000000000000000000000000000000000000000000000000000000000000000000000000000000000000000000000000000000000000000000000000000000000000000000000000000000000000000000000 ,
10
12
b00000000000000000000000000000000110111101010110110111110111011110000000000000000000000000000000000000000000000000000000000000000000000000000000000000000000000000000000000000000000000000000000000000000000000000000000000000000000000000000000000000000000000000000000000000000000000000000000000000000000000000000000000000000000000000000000000000000000000000000000000000000000000000000000000000000000000000000000000000000000000000000000000000000000000000000000000000000000000000000000000000000000000000000000000000000 3
#87500000
0!
0)
00
#90000000
1!
0#
b00000000000000000000000000000000000000000000000000000000000000000000000000000000000000000000000000000000000000000000000000000000000000000000000000000000000000000000000000000000000000000000000000000000000000000000000000000000000000000000000000000000000000000000000000000000000000000000000000000000000000000000000000000000000000000000000000000000000000000000000000000000000000000000000000000000000000000000000000000000000000000000000000000000000000000000000000000000000000000000000000000000000000000000000000000000 $
b00010010 (
1)
0+
b00000000000000000000000000000000000000000000000000000000000000000000000000000000000000000000000000000000000000000000000000000000000000000000000000000000000000000000000000000000000000000000000000000000000000000000000000000000000000000000000000000000000000000000000000000000000000000000000000000000000000000000000000000000000000000000000000000000000000000000000000000000000000000000000000000000000000000000000000000000000000000000000000000000000000000000000000000000000000000000000000000000000000000000000000000000 ,
10
02
b00000000000000000000000000000000000000000000000000000000000000000000000000000000000000000000000000000000000000000000000000000000000000000000000000000000000000000000000000000000000000000000000000000000000000000000000000000000000000000000000000000000000000000000000000000000000000000000000000000000000000000000000000000000000000000000000000000000000000000000000000000000000000000000000000000000000000000000000000000000000000000000000000000000000000000000000000000000000000000000000000000000000000000000000000000000 3
b0100000000000000 7
#92500000
0!
0)
00
#95000000
1!
1'
b00010011 (
1)
1/
10
16
b0000000000000000 7
#97500000
0!
0)
00
#100000000
1!
0'
b00010100 (
1)
0/
10
06
#102500000
0!
0)
00
#105000000
1!
b00010101 (
1)
10
#107500000
0!
0)
00
#110000000
1!
b00010110 (
1)
10
#112500000
0!
0)
00
#115000000
1!
b00010111 (
1)
10
#117500000
0!
0)
00
#120000000
1!
b00011000 (
1)
10
#122500000
0!
0)
00
#125000000
1!
b00011001 (
1)
10
#127500000
0!
0)
00
#130000000
1!
b00011010 (
1)
10
#132500000
0!
0)
00
#135000000
1!
b00011011 (
1)
10
#137500000
0!
0)
00
#140000000
1!
b00011100 (
1)
10
#142500000
0!
0)
00
#145000000
1!
b00011101 (
1)
10
#147500000
0!
0)
00
#150000000
1!
b00011110 (
1)
10
#152500000
0!
0)
00
#155000000
1!
b00011111 (
1)
10
#157500000
0!
0)
00
#160000000
1!
b00100000 (
1)
10
#162500000
0!
0)
00
#165000000
1!
b00100001 (
1)
10
#167500000
0!
0)
00
#170000000
1!
b00100010 (
1)
10
#172500000
0!
0)
00
#175000000
1!
b00100011 (
1)
10
#177500000
0!
0)
00
#180000000
1!
b00100100 (
1)
10
#182500000
0!
0)
00
#185000000
1!
b00100101 (
1)
10
#187500000
0!
0)
00
#190000000
1!
b00100110 (
1)
10
#192500000
0!
0)
00
#195000000
1!
b00100111 (
1)
10
#197500000
0!
0)
00
#200000000
1!
b00101000 (
1)
10
#202500000
0!
0)
00
#205000000
1!
b00101001 (
1)
10
#207500000
0!
0)
00
#210000000
1!
b00101010 (
1)
10
#212500000
0!
0)
00
#215000000
1!
b00101011 (
1)
10
#217500000
0!
0)
00
#220000000
1!
b00101100 (
1)
10
#222500000
0!
0)
00
#225000000
1!
b00101101 (
1)
10
#227500000
0!
0)
00
#230000000
1!
b00101110 (
1)
10
#232500000
0!
0)
00
#235000000
1!
b00101111 (
1)
10
#237500000
0!
0)
00
#240000000
1!
b00110000 (
1)
10
#242500000
0!
0)
00
#245000000
1!
b00110001 (
1)
10
#247500000
0!
0)
00
#250000000
1!
b00110010 (
1)
10
#252500000
0!
0)
00
#255000000
1!
b00110011 (
1)
10
#257500000
0!
0)
00
#260000000
1!
b00110100 (
1)
10
#262500000
0!
0)
00
#265000000
1!
b00110101 (
1)
10
#267500000
0!
0)
00
#270000000
1!
b00110110 (
1)
10
#272500000
0!
0)
00
#275000000
1!
b00110111 (
1)
10
#277500000
0!
0)
00
#280000000
1!
b00111000 (
1)
10
#282500000
0!
0)
00
#285000000
1!
b00111001 (
1)
10
#287500000
0!
0)
00
#290000000
1!
b00111010 (
1)
10
#292500000
0!
0)
00
#295000000
1!
b00111011 (
1)
10
#297500000
0!
0)
00
#300000000
1!
b00111100 (
1)
10
#302500000
0!
0)
00
#305000000
1!
b00111101 (
1)
10
#307500000
0!
0)
00
#310000000
1!
b00111110 (
1)
10
#312500000
0!
0)
00
#315000000
1!
b00111111 (
1)
10
#317500000
0!
0)
00
#320000000
1!
b01000000 (
1)
10
#322500000
0!
0)
00
#325000000
1!
b01000001 (
1)
10
#327500000
0!
0)
00
#330000000
1!
b01000010 (
1)
10
#332500000
0!
0)
00
#335000000
1!
b01000011 (
1)
10
#337500000
0!
0)
00
#340000000
1!
b01000100 (
1)
10
#342500000
0!
0)
00
#345000000
1!
b01000101 (
1)
10
#347500000
0!
0)
00
#350000000
1!
b01000110 (
1)
10
#352500000
0!
0)
00
#355000000
1!
b01000111 (
1)
10
#357500000
0!
0)
00
#360000000
1!
b01001000 (
1)
10
#362500000
0!
0)
00
#365000000
1!
b01001001 (
1)
10
#367500000
0!
0)
00
#370000000
1!
b01001010 (
1)
10
#372500000
0!
0)
00
#375000000
1!
b01001011 (
1)
10
#377500000
0!
0)
00
#380000000
1!
b01001100 (
1)
10
#382500000
0!
0)
00
#385000000
1!
b01001101 (
1)
10
#387500000
0!
0)
00
#390000000
1!
b01001110 (
1)
10
#392500000
0!
0)
00
#395000000
1!
b01001111 (
1)
10
#397500000
0!
0)
00
#400000000
1!
b01010000 (
1)
10
#402500000
0!
0)
00
#405000000
1!
b01010001 (
1)
10
#407500000
0!
0)
00
#410000000
1!
b01010010 (
1)
10
#412500000
0!
0)
00
#415000000
1!
b01010011 (
1)
10
#417500000
0!
0)
00
#420000000
1!
b01010100 (
1)
10
#422500000
0!
0)
00
#425000000
1!
b01010101 (
1)
10
#427500000
0!
0)
00
#430000000
1!
b01010110 (
1)
10
#432500000
0!
0)
00
#435000000
1!
b01010111 (
1)
10
#437500000
0!
0)
00
#440000000
1!
b01011000 (
1)
10
#442500000
0!
0)
00
#445000000
1!
b01011001 (
1)
10
#447500000
0!
0)
00
#450000000
1!
b01011010 (
1)
10
#452500000
0!
0)
00
#455000000
1!
b01011011 (
1)
10
#457500000
0!
0)
00
#460000000
1!
b01011100 (
1)
10
#462500000
0!
0)
00
#465000000
1!
b01011101 (
1)
10
#467500000
0!
0)
00
#470000000
1!
b01011110 (
1)
10
#472500000
0!
0)
00
#475000000
1!
b01011111 (
1)
10
#477500000
0!
0)
00
#480000000
1!
b01100000 (
1)
10
#482500000
0!
0)
00
#485000000
1!
b01100001 (
1)
10
#487500000
0!
0)
00
#490000000
1!
b01100010 (
1)
10
#492500000
0!
0)
00
#495000000
1!
b01100011 (
1)
10
#497500000
0!
0)
00
#500000000
1!
b01100100 (
1)
10
#502500000
0!
0)
00
#505000000
1!
b01100101 (
1)
10
#507500000
0!
0)
00
#510000000
1!
b01100110 (
1)
10
#512500000
0!
0)
00
#515000000
1!
b01100111 (
1)
10
#517500000
0!
0)
00
#520000000
1!
b01101000 (
1)
10
#522500000
0!
0)
00
#525000000
1!
b01101001 (
1)
10
#527500000
0!
0)
00
#530000000
1!
b01101010 (
1)
10
#532500000
0!
0)
00
#535000000
1!
b01101011 (
1)
10
#537500000
0!
0)
00
#540000000
1!
b01101100 (
1)
10
#542500000
0!
0)
00
#545000000
1!
b01101101 (
1)
10
#547500000
0!
0)
00
#550000000
1!
b01101110 (
1)
10
#552500000
0!
0)
00
#555000000
1!
b01101111 (
1)
10
#557500000
0!
0)
00
#560000000
1!
b01110000 (
1)
10
#562500000
0!
0)
00
#565000000
1!
b01110001 (
1)
10
#567500000
0!
0)
00
#570000000
1!
b01110010 (
1)
10
#572500000
0!
0)
00
#575000000
1!
b01110011 (
1)
10
#577500000
0!
0)
00
#580000000
1!
b01110100 (
1)
10
#582500000
0!
0)
00
#585000000
1!
b01110101 (
1)
10
#587500000
0!
0)
00
#590000000
1!
b01110110 (
1)
10
#592500000
0!
0)
00
#595000000
1!
b01110111 (
1)
10
#597500000
0!
0)
00
#600000000
1!
b01111000 (
1)
10
#602500000
0!
0)
00
#605000000
1!
b01111001 (
1)
10
#607500000
0!
0)
00
#610000000
1!
b01111010 (
1)
10
#612500000
0!
0)
00
#615000000
1!
b01111011 (
1)
10
#617500000
0!
0)
00
#620000000
1!
b01111100 (
1)
10
#622500000
0!
0)
00
#625000000
1!
b01111101 (
1)
10
#627500000
0!
0)
00
#630000000
1!
b01111110 (
1)
10
#632500000
0!
0)
00
#635000000
1!
b01111111 (
1)
10
#637500000
0!
0)
00
#640000000
1!
b10000000 (
1)
10
#642500000
0!
0)
00
#645000000
1!
b10000001 (
1)
10
#647500000
0!
0)
00
#650000000
1!
b10000010 (
1)
10
#652500000
0!
0)
00
